pip_ensure_version/__init__.py
pip_ensure_version/pip_ensure_version.py
pip_ensure_version-1.0.1.dist-info/LICENSE
pip_ensure_version-1.0.1.dist-info/METADATA
pip_ensure_version-1.0.1.dist-info/WHEEL
pip_ensure_version-1.0.1.dist-info/top_level.txt
pip_ensure_version-1.0.1.dist-info/RECORD
