Metadata-Version: 2.1
Name: pip-ensure-version
Version: 1.0.1
Summary: Ensure pip package version, and auto update if not
Home-page: https://github.com/soraxas/pip-ensure-version
Author: Tin Lai (@soraxas)
Author-email: oscar@tinyiu.com
License: MIT
Requires-Python: >=3.6
License-File: LICENSE
Requires-Dist: pip
